<configs>
  <!--
  config/@url - can be either http://file.zip , file:/folder
  -->
  <config name="bz_config"
    title="Birzeit Test Config"
    url="http://bungeni-editor.googlecode.com/svn/BungeniEditor_configs/alltypesdev.zip"
    folder-base="../../Editor_configs/bz_configs"
    receiver="org.bungeni.editor.input.FSDocumentReceiver"
    />

  <config name="allTypesDev"
    title="All Types Development"
    url="http://bungeni-editor.googlecode.com/svn/BungeniEditor_configs/alltypesdev.zip"
    folder-base="../../Editor_configs/development_configs"
    receiver="org.bungeni.editor.input.FSDocumentReceiver"
  default="true"

	/>
  <config name="Bill-Bungeni"
    title="Bill Bungeni Integration"
    url="http://bungeni-editor.googlecode.com/svn/BungeniEditor_configs/bill-bungeni.zip"
    folder-base="../../Editor_configs/bungeni_configs"
    receiver="org.bungeni.ext.integration.bungeniportal.BungeniDocumentReceiver"
  
  >
	
 

  <custom>
       <login server="10.0.2.2" port="8081" baseurl="login" />
       <!-- authorize-uri = entry point to oauth
       authorize-form-uri = uri to authorize form to actually autorize after login  -->
       <oauth app-id="bungeni_editor" 
         secret="2000bc6f803955e9829d01a9b13e56d1ea0e811d" 
         authorize-uri="/oauth/authorize?client_id={0}&amp;client_secret={1}&amp;response_type=code&amp;state={2}"
         authorize-form-uri="/oauth/authorize-form"
         refresh-token-uri="/oauth/access-token?grant_type=refresh_token&amp;refresh_token={0}"
         access-token-uri="/oauth/access-token?client_id={0}&amp;grant_type=authorization_code&amp;code={1}"
        >
         <!--
          <props>
             <key name="refresh_code" value="" />
             <key name="authorization_code" value="" />
          </props> -->
        </oauth>
       <search base="/workspace/my-documents/external/jsonlisting?start=0&amp;limit=100" />
       <document base="/workspace/my-documents/external/" />
    </custom> 
    </config>
</configs>