<?xml version="1.0" encoding="windows-1252"?>

<!--
    Document   : selector_dialogs.xml
    Created on : January 23, 2012, 5:18 PM
    For main container dialogs not specifying the class defaults the container
    class to org.bungeni.editor.selectors.general.Main
-->

<dialogs>
    <dialog id="billsMain" >
        <dialog
            class="org.bungeni.editor.selectors.debaterecord.bills.Bills"
             />
    </dialog>

    <dialog id="namedSectionMain" >
        <dialog
            class="org.bungeni.editor.selectors.debaterecord.general.NamedSection"
             />
    </dialog>


    <dialog id="motionsMain"
        class="org.bungeni.editor.selectors.debaterecord.motions.Main" >
        <dialog  class="org.bungeni.editor.selectors.debaterecord.motions.MotionNameAndURI"
             />
        <dialog class="org.bungeni.editor.selectors.debaterecord.motions.MotionSelect"
             />
        <dialog class="org.bungeni.editor.selectors.debaterecord.motions.MotionText"
             />
        <dialog  class="org.bungeni.editor.selectors.debaterecord.motions.MotionTitle"
             />
    </dialog>

    <dialog id="questionMain"
        class="org.bungeni.editor.selectors.debaterecord.question.Main" >
        <dialog class="org.bungeni.editor.selectors.debaterecord.question.QuestionAddressedTo"
             />
        <dialog class="org.bungeni.editor.selectors.debaterecord.question.QuestionNo"
             />
        <dialog
            class="org.bungeni.editor.selectors.debaterecord.question.QuestionerNameAndURI"
             />

    </dialog>

    <dialog id="documentsSingleSelect"
        class="org.bungeni.editor.selectors.debaterecord.tableddocuments.MainSingleSelect" >
        <dialog
            class="org.bungeni.editor.selectors.debaterecord.tableddocuments.SingleSelectTabledDocuments"
             />

    </dialog>

    <dialog id="questionsMain"
        class="org.bungeni.editor.selectors.debaterecord.questions.Main" >
        <dialog
            class="org.bungeni.editor.selectors.debaterecord.questions.QuestionType"
             />

    </dialog>

    <dialog id="conclusionMain">
        <dialog
            class="org.bungeni.editor.selectors.debaterecord.conclusion.HouseClosingTime"
             />
    </dialog>

    <dialog id="documentsMain"
        class="org.bungeni.editor.selectors.debaterecord.tableddocuments.Main" >
        <dialog
            class="org.bungeni.editor.selectors.debaterecord.tableddocuments.TabledDocuments"
             />
    </dialog>

    <dialog id="motionsMainEdit"
        class="org.bungeni.editor.selectors.debaterecord.motions.MainEdit" >
        <dialog
            class="org.bungeni.editor.selectors.debaterecord.motions.MotionNameAndURI"
             />
    </dialog>

    <dialog id="refMain">
        <dialog
            class="org.bungeni.editor.selectors.general.ref.RefURI"
             />

    </dialog>

    <dialog id="classMain" >
        <dialog
            class="org.bungeni.editor.selectors.general.ref.RefClass"
             />

    </dialog>

    <dialog id="speechMain"
        class="org.bungeni.editor.selectors.debaterecord.speech.Main" >
        <dialog
            class="org.bungeni.editor.selectors.debaterecord.speech.PersonSelector"
             />
        <dialog
            class="org.bungeni.editor.selectors.debaterecord.speech.PersonURI"
             />
        <dialog
            class="org.bungeni.editor.selectors.debaterecord.speech.SpeechAs"
             />
        <dialog
            class="org.bungeni.editor.selectors.debaterecord.speech.SpeechBy"
             />
    </dialog>

    <dialog id="speechMainEdit"
        class="org.bungeni.editor.selectors.debaterecord.speech.MainEdit" >
        <dialog
            class="org.bungeni.editor.selectors.debaterecord.speech.PersonSelector"
             />
        <dialog
            class="org.bungeni.editor.selectors.debaterecord.speech.PersonURI"
             />
        <dialog
            class="org.bungeni.editor.selectors.debaterecord.speech.SpeechAs"
             />
        <dialog
            class="org.bungeni.editor.selectors.debaterecord.speech.SpeechBy"
             />
    </dialog>

    <dialog id="documentsMainDataEntry"
        class="org.bungeni.editor.selectors.debaterecord.tableddocuments.MainDataEntry" >
        <dialog
            class="org.bungeni.editor.selectors.debaterecord.tableddocuments.EnterTabledDocument"
             />
    </dialog>

    <dialog id="documentLogo"
        class="org.bungeni.editor.selectors.debaterecord.masthead.Main" >
        <dialog
            class="org.bungeni.editor.selectors.debaterecord.masthead.DebateRecordLogo"
             />
    </dialog>

    <dialog id="committeesMain"
        class="org.bungeni.editor.selectors.debaterecord.committees.Main" >
        <dialog
            class="org.bungeni.editor.selectors.debaterecord.committees.Committees"
             />
    </dialog>



    <dialog id="questionEdit"
        class="org.bungeni.editor.selectors.debaterecord.question.MainEdit" >

        <dialog
            class="org.bungeni.editor.selectors.debaterecord.question.QuestionAddressedTo"
             />
        <dialog
            class="org.bungeni.editor.selectors.debaterecord.question.QuestionSelect"
             />
        <dialog
            class="org.bungeni.editor.selectors.debaterecord.question.QuestionText"
             />
        <dialog
            class="org.bungeni.editor.selectors.debaterecord.question.QuestionTitle"
             />
        <dialog
            class="org.bungeni.editor.selectors.debaterecord.question.QuestionerNameAndURI"
             />

    </dialog>


</dialogs>